{
    "id": "hist-1950",
    "type": "experiment",
    "experiment_id": "hist-1950",
    "activity_id": [
        "highresmip"
    ],
    "additional_allowed_model_components": [
        "aer"
    ],
    "description": "Coupled integrations with historic external forcings (as in highresSST-present)",
    "end_year": 2014,
    "experiment": "coupled historical 1950-2014",
    "min_number_yrs_per_sim": "65",
    "parent_activity_id": [
        "highresmip"
    ],
    "parent_experiment_id": [
        "spinup-1950"
    ],
    "required_model_components": [
        "aogcm"
    ],
    "start_year": 1950,
    "sub_experiment_id": [
        "none"
    ],
    "tier": "2"
}