{
  "@id": "mip-cmor-tables:organisations/consortia/e3sm-project",
  "@type": "consortium",
  "consortia:status": "active",
  "consortium:changes": "",
  "consortium:cmip-acronym": "E3SM-Project",
  "consortium:description": "E3SM-Project",
  "consortium:members": {
    "@set": [
      {
        "@type": "consortia:member",
        "consortia:dates": [
          {
            "from": 2016,
            "phase": "CMIP6",
            "to": 2022
          }
        ],
        "consortia:institution": {
          "@id": "mip-cmor-tables:organisations/institutions/llnl"
        },
        "consortia:membership-type": "active"
      },
      {
        "@type": "consortia:member",
        "consortia:dates": [
          {
            "from": 2016,
            "phase": "CMIP6",
            "to": 2022
          }
        ],
        "consortia:institution": {
          "@id": "mip-cmor-tables:organisations/institutions/anl"
        },
        "consortia:membership-type": "prior"
      },
      {
        "@type": "consortia:member",
        "consortia:dates": [
          {
            "from": 2016,
            "phase": "CMIP6",
            "to": 2022
          }
        ],
        "consortia:institution": {
          "@id": "mip-cmor-tables:organisations/institutions/bnl"
        },
        "consortia:membership-type": "prior"
      },
      {
        "@type": "consortia:member",
        "consortia:dates": [
          {
            "from": 2016,
            "phase": "CMIP6",
            "to": 2022
          }
        ],
        "consortia:institution": {
          "@id": "mip-cmor-tables:organisations/institutions/lanl"
        },
        "consortia:membership-type": "prior"
      },
      {
        "@type": "consortia:member",
        "consortia:dates": [
          {
            "from": 2016,
            "phase": "CMIP6",
            "to": 2022
          }
        ],
        "consortia:institution": {
          "@id": "mip-cmor-tables:organisations/institutions/lbnl"
        },
        "consortia:membership-type": "prior"
      },
      {
        "@type": "consortia:member",
        "consortia:dates": [
          {
            "from": 2016,
            "phase": "CMIP6",
            "to": 2022
          }
        ],
        "consortia:institution": {
          "@id": "mip-cmor-tables:organisations/institutions/ornl"
        },
        "consortia:membership-type": "prior"
      },
      {
        "@type": "consortia:member",
        "consortia:dates": [
          {
            "from": 2016,
            "phase": "CMIP6",
            "to": 2022
          }
        ],
        "consortia:institution": {
          "@id": "mip-cmor-tables:organisations/institutions/pnnl"
        },
        "consortia:membership-type": "prior"
      },
      {
        "@type": "consortia:member",
        "consortia:dates": [
          {
            "from": 2016,
            "phase": "CMIP6",
            "to": 2022
          }
        ],
        "consortia:institution": {
          "@id": "mip-cmor-tables:organisations/institutions/snl"
        },
        "consortia:membership-type": "prior"
      }
    ]
  },
  "consortium:url": ""
}
