{
  "@id": "mip-cmor-tables:miptables/variables/table-specific/ap3hrptlev-clws",
  "@type": "table-variable",
  "variable:branded_variable_name": "clws_3hr-ap-tpt-l-hxy",
  "variable:comment": "Calculated as the mass of stratiform cloud liquid water in the grid cell divided by the mass of air (including the water in all phases) in the grid cell.  This includes precipitating hydrometeors ONLY if the precipitating hydrometeors affect the calculation of radiative transfer in model.",
  "variable:dimensions": [
    "longitude",
    "latitude",
    "alevel",
    "time1"
  ],
  "variable:frequency": "3hrPt",
  "variable:generic": {
    "@id": "mip-cmor-tables:miptables/variables/generic/clws"
  },
  "variable:modelling_realms": [
    {
      "@id": "mip-cmor-tables:modellingrealms/atmos"
    }
  ],
  "variable:provenance": {
    "@id": "mip-cmor-tables:miptables/provenance/ap3hrptlev-clws"
  },
  "variable:validation": {
    "ok_max_mean_abs": "",
    "ok_min_mean_abs": "",
    "valid_max": "",
    "valid_min": ""
  }
}
