{
  "@id": "mip-cmor-tables:miptables/variables/table-specific/apday-huss",
  "@type": "table-variable",
  "variable:branded_variable_name": "huss_day-ap-tav-h02-hxy",
  "variable:comment": "Near-surface (usually, 2 meter) specific humidity.",
  "variable:dimensions": [
    "longitude",
    "latitude",
    "time",
    "height2m"
  ],
  "variable:frequency": "day",
  "variable:generic": {
    "@id": "mip-cmor-tables:miptables/variables/generic/huss"
  },
  "variable:modelling_realms": [
    {
      "@id": "mip-cmor-tables:modellingrealms/atmos"
    }
  ],
  "variable:provenance": {
    "@id": "mip-cmor-tables:miptables/provenance/apday-huss"
  },
  "variable:validation": {
    "ok_max_mean_abs": "",
    "ok_min_mean_abs": "",
    "valid_max": "",
    "valid_min": ""
  }
}
