{
  "@id": "mip-cmor-tables:miptables/variables/table-specific/apmonz-wtem",
  "@type": "table-variable",
  "variable:branded_variable_name": "wtem_mon-ap-tav-p39-hy",
  "variable:comment": "Transformed Eulerian Mean Diagnostics w*, upward component of the residual meridional circulation (v*, w*) derived from 6 hr or higher frequency data fields (use instantaneous daily fields or 12 hr fields if the 6 hr data are not available). Scale height: 6950 m",
  "variable:dimensions": [
    "latitude",
    "plev39",
    "time"
  ],
  "variable:frequency": "mon",
  "variable:generic": {
    "@id": "mip-cmor-tables:miptables/variables/generic/wtem"
  },
  "variable:modelling_realms": [
    {
      "@id": "mip-cmor-tables:modellingrealms/atmos"
    }
  ],
  "variable:provenance": {
    "@id": "mip-cmor-tables:miptables/provenance/apmonz-wtem"
  },
  "variable:validation": {
    "ok_max_mean_abs": "",
    "ok_min_mean_abs": "",
    "valid_max": "",
    "valid_min": ""
  }
}
