{
  "@id": "mip-cmor-tables:miptables/variables/table-specific/apmon-ua7h",
  "@type": "table-variable",
  "variable:branded_variable_name": "ua_mon-ap-tav-p7h-hxy",
  "variable:comment": "Zonal wind (positive in a eastward direction).",
  "variable:dimensions": [
    "longitude",
    "latitude",
    "plev7h",
    "time"
  ],
  "variable:frequency": "mon",
  "variable:generic": {
    "@id": "mip-cmor-tables:miptables/variables/generic/ua7h"
  },
  "variable:modelling_realms": [
    {
      "@id": "mip-cmor-tables:modellingrealms/atmos"
    }
  ],
  "variable:provenance": {
    "@id": "mip-cmor-tables:miptables/provenance/apmon-ua7h"
  },
  "variable:validation": {
    "ok_max_mean_abs": "",
    "ok_min_mean_abs": "",
    "valid_max": "",
    "valid_min": ""
  }
}
