{
  "@id": "mip-cmor-tables:miptables/variables/table-specific/apsubhrpt-huss",
  "@type": "table-variable",
  "variable:branded_variable_name": "huss_subhr-ap-tpt-h02-hxy",
  "variable:comment": "Near-surface (usually, 2 meter) specific humidity.",
  "variable:dimensions": [
    "longitude",
    "latitude",
    "time1",
    "height2m"
  ],
  "variable:frequency": "subhrPt",
  "variable:generic": {
    "@id": "mip-cmor-tables:miptables/variables/generic/huss"
  },
  "variable:modelling_realms": [
    {
      "@id": "mip-cmor-tables:modellingrealms/atmos"
    }
  ],
  "variable:provenance": {
    "@id": "mip-cmor-tables:miptables/provenance/apsubhrpt-huss"
  },
  "variable:validation": {
    "ok_max_mean_abs": "",
    "ok_min_mean_abs": "",
    "valid_max": "",
    "valid_min": ""
  }
}
