{
  "@id": "mip-cmor-tables:miptables/variables/table-specific/lpday-mrtws",
  "@type": "table-variable",
  "variable:branded_variable_name": "mrtws_day-ld-tav-z0-hxy",
  "variable:comment": "Mass of water in all phases and in all components including soil, canopy, vegetation, ice sheets, rivers and ground water.",
  "variable:dimensions": [
    "longitude",
    "latitude",
    "time"
  ],
  "variable:frequency": "day",
  "variable:generic": {
    "@id": "mip-cmor-tables:miptables/variables/generic/mrtws"
  },
  "variable:modelling_realms": [
    {
      "@id": "mip-cmor-tables:modellingrealms/land"
    }
  ],
  "variable:provenance": {
    "@id": "mip-cmor-tables:miptables/provenance/lpday-mrtws"
  },
  "variable:validation": {
    "ok_max_mean_abs": "",
    "ok_min_mean_abs": "",
    "valid_max": "",
    "valid_min": ""
  }
}
