{
  "@id": "mip-cmor-tables:miptables/variables/table-specific/obyrlev-pcalc",
  "@type": "table-variable",
  "variable:branded_variable_name": "pcalc_yr-oc-tav-l-hxy",
  "variable:comment": "Production rate of Calcite, a mineral that is a polymorph of calcium carbonate. The chemical formula of calcite is CaCO3. ",
  "variable:dimensions": [
    "longitude",
    "latitude",
    "olevel",
    "time"
  ],
  "variable:frequency": "yr",
  "variable:generic": {
    "@id": "mip-cmor-tables:miptables/variables/generic/pcalc"
  },
  "variable:modelling_realms": [
    {
      "@id": "mip-cmor-tables:modellingrealms/ocnbgchem"
    }
  ],
  "variable:provenance": {
    "@id": "mip-cmor-tables:miptables/provenance/obyrlev-pcalc"
  },
  "variable:validation": {
    "ok_max_mean_abs": "",
    "ok_min_mean_abs": "",
    "valid_max": "",
    "valid_min": ""
  }
}
