{
  "@id": "mip-cmor-tables:miptables/variables/table-specific/simon-sifb",
  "@type": "table-variable",
  "variable:branded_variable_name": "sifb_mon-si-tav-z0-hxy",
  "variable:comment": "Mean height of sea-ice surface (=snow-ice interface when snow covered) above sea level",
  "variable:dimensions": [
    "longitude",
    "latitude",
    "time"
  ],
  "variable:frequency": "mon",
  "variable:generic": {
    "@id": "mip-cmor-tables:miptables/variables/generic/sifb"
  },
  "variable:modelling_realms": [
    {
      "@id": "mip-cmor-tables:modellingrealms/seaice"
    }
  ],
  "variable:provenance": {
    "@id": "mip-cmor-tables:miptables/provenance/simon-sifb"
  },
  "variable:validation": {
    "ok_max_mean_abs": "",
    "ok_min_mean_abs": "",
    "valid_max": "",
    "valid_min": ""
  }
}
